py_simple_email/__init__.py
py_simple_email/main.py
py_simple_email-1.0.0.dist-info/LICENSE
py_simple_email-1.0.0.dist-info/METADATA
py_simple_email-1.0.0.dist-info/WHEEL
py_simple_email-1.0.0.dist-info/top_level.txt
py_simple_email-1.0.0.dist-info/RECORD
