Metadata-Version: 2.1
Name: py-simple-email
Version: 1.0.0
Summary: Python Simple Fast Email Sending without External Libs
Home-page: https://github.com/sannjayy/py-simple-email
Author: Sanjay Sikdar
Author-email: me@sanjaysikdar.dev
License: MIT
Project-URL: Bug Reports, https://github.com/sannjayy/py-simple-email/issues
Project-URL: Funding, https://www.paypal.com/paypalme/znasofficial
Project-URL: Say Thanks!, https://saythanks.io/to/sannjayy
Project-URL: Source, https://github.com/sannjayy/py-simple-email/
Keywords: python,smtp,email send,python send email
Classifier: Development Status :: 5 - Production/Stable
Classifier: Intended Audience :: Developers
Classifier: Topic :: Software Development :: Libraries :: Python Modules
Classifier: Operating System :: OS Independent
Classifier: License :: OSI Approved :: MIT License
Classifier: Programming Language :: Python :: 3.9
Classifier: Programming Language :: Python :: 3.10
Classifier: Programming Language :: Python :: 3.11
Classifier: Programming Language :: Python :: 3.12
Requires-Python: >=3.8, <4
License-File: LICENSE
